testwknd/__init__.py
testwknd/pdf2image.py
testwknd/pdf2text.py
testwknd-1.0.2.dist-info/LICENSE
testwknd-1.0.2.dist-info/METADATA
testwknd-1.0.2.dist-info/WHEEL
testwknd-1.0.2.dist-info/top_level.txt
testwknd-1.0.2.dist-info/RECORD
