Metadata-Version: 2.2
Name: testwknd
Version: 1.0.2
Summary: I'm on my way
Author: 1nfinity
Author-email: edmond.nistor723@gmail.com
License-File: LICENSE
Dynamic: author
Dynamic: author-email
Dynamic: description
Dynamic: description-content-type
Dynamic: summary
